torchlmdb.py
torchlmdb-0.1.1.dist-info/LICENSE.md
torchlmdb-0.1.1.dist-info/METADATA
torchlmdb-0.1.1.dist-info/WHEEL
torchlmdb-0.1.1.dist-info/top_level.txt
torchlmdb-0.1.1.dist-info/RECORD
