Metadata-Version: 2.1
Name: torchlmdb
Version: 0.1.1
Summary: Simple Implementation of a drop-in database for image datasets in PyTorch.
Home-page: https://github.com/JonasGeiping/torchlmdb
Author: Jonas Geiping
Author-email: jonas.geiping@gmail.com
License: MIT
Keywords: PyTorch,torchvision,LMDB
Platform: any
Classifier: Topic :: Database
Classifier: License :: OSI Approved :: MIT License
Classifier: Operating System :: OS Independent
Classifier: Programming Language :: Python
Requires-Python: >=3.7
License-File: LICENSE.md
Requires-Dist: torch (>=1.10)
Requires-Dist: torchvision
Requires-Dist: lmdb
